<?

$opcodes = array(
    array('nop', 0, 0),
    array('aconst_null', 1, 0),
    array('iconst_m1', 2, 0),
    array('iconst_0', 3, 0),
    array('iconst_1', 4, 0),
    array('iconst_2', 5, 0),
    array('iconst_3', 6, 0),
    array('iconst_4', 7, 0),
    array('iconst_5', 8, 0),
    array('lconst_0', 9, 0),
    array('lconst_1', 10, 0),
    array('fconst_0', 11, 0),
    array('fconst_1', 12, 0),
    array('fconst_2', 13, 0),
    array('dconst_0', 14, 0),
    array('dconst_1', 15, 0),
    array('bipush', 16, 1),
    array('sipush', 17, 2),
    array('ldc', 18, 1),
    array('ldc_w', 19, 2),
    array('ldc2_w', 20, 2),
    array('iload', 21, 1),
    array('lload', 22, 1),
    array('fload', 23, 1),
    array('dload', 24, 1),
    array('aload', 25, 1),
    array('iload_0', 26, 0),
    array('iload_1', 27, 0),
    array('iload_2', 28, 0),
    array('iload_3', 29, 0),
    array('lload_0', 30, 0),
    array('lload_1', 31, 0),
    array('lload_2', 32, 0),
    array('lload_3', 33, 0),
    array('fload_0', 34, 0),
    array('fload_1', 35, 0),
    array('fload_2', 36, 0),
    array('fload_3', 37, 0),
    array('dload_0', 38, 0),
    array('dload_1', 39, 0),
    array('dload_2', 40, 0),
    array('dload_3', 41, 0),
    array('aload_0', 42, 0),
    array('aload_1', 43, 0),
    array('aload_2', 44, 0),
    array('aload_3', 45, 0),
    array('iaload', 46, 0),
    array('laload', 47, 0),
    array('faload', 48, 0),
    array('daload', 49, 0),
    array('aaload', 50, 0),
    array('baload', 51, 0),
    array('caload', 52, 0),
    array('saload', 53, 0),
    array('istore', 54, 1),
    array('lstore', 55, 1),
    array('fstore', 56, 1),
    array('dstore', 57, 1),
    array('astore', 58, 1),
    array('istore_0', 59, 0),
    array('istore_1', 60, 0),
    array('istore_2', 61, 0),
    array('istore_3', 62, 0),
    array('lstore_0', 63, 0),
    array('lstore_1', 64, 0),
    array('lstore_2', 65, 0),
    array('lstore_3', 66, 0),
    array('fstore_0', 67, 0),
    array('fstore_1', 68, 0),
    array('fstore_2', 69, 0),
    array('fstore_3', 70, 0),
    array('dstore_0', 71, 0),
    array('dstore_1', 72, 0),
    array('dstore_2', 73, 0),
    array('dstore_3', 74, 0),
    array('astore_0', 75, 0),
    array('astore_1', 76, 0),
    array('astore_2', 77, 0),
    array('astore_3', 78, 0),
    array('iastore', 79, 0),
    array('lastore', 80, 0),
    array('fastore', 81, 0),
    array('dastore', 82, 0),
    array('aastore', 83, 0),
    array('bastore', 84, 0),
    array('castore', 85, 0),
    array('sastore', 86, 0),
    array('pop', 87, 0),
    array('pop2', 88, 0),
    array('dup', 89, 0),
    array('dup_x1', 90, 0),
    array('dup_x2', 91, 0),
    array('dup2', 92, 0),
    array('dup2_x1', 93, 0),
    array('dup2_x2', 94, 0),
    array('swap', 95, 0),
    array('iadd', 96, 0),
    array('ladd', 97, 0),
    array('fadd', 98, 0),
    array('dadd', 99, 0),
    array('isub', 100, 0),
    array('lsub', 101, 0),
    array('fsub', 102, 0),
    array('dsub', 103, 0),
    array('imul', 104, 0),
    array('lmul', 105, 0),
    array('fmul', 106, 0),
    array('dmul', 107, 0),
    array('idiv', 108, 0),
    array('ldiv', 109, 0),
    array('fdiv', 110, 0),
    array('ddiv', 111, 0),
    array('irem', 112, 0),
    array('lrem', 113, 0),
    array('frem', 114, 0),
    array('drem', 115, 0),
    array('ineg', 116, 0),
    array('lneg', 117, 0),
    array('fneg', 118, 0),
    array('dneg', 119, 0),
    array('ishl', 120, 0),
    array('lshl', 121, 0),
    array('ishr', 122, 0),
    array('lshr', 123, 0),
    array('iushr', 124, 0),
    array('lushr', 125, 0),
    array('iand', 126, 0),
    array('land', 127, 0),
    array('ior', 128, 0),
    array('lor', 129, 0),
    array('ixor', 130, 0),
    array('lxor', 131, 0),
    array('iinc', 132, 2),
    array('i2l', 133, 0),
    array('i2f', 134, 0),
    array('i2d', 135, 0),
    array('l2i', 136, 0),
    array('l2f', 137, 0),
    array('l2d', 138, 0),
    array('f2i', 139, 0),
    array('f2l', 140, 0),
    array('f2d', 141, 0),
    array('d2i', 142, 0),
    array('d2l', 143, 0),
    array('d2f', 144, 0),
    array('i2b', 145, 0),
    array('i2c', 146, 0),
    array('i2s', 147, 0),
    array('lcmp', 148, 0),
    array('fcmpl', 149, 0),
    array('fcmpg', 150, 0),
    array('dcmpl', 151, 0),
    array('dcmpg', 152, 0),
    array('ifeq', 153, 2),
    array('ifne', 154, 2),
    array('iflt', 155, 2),
    array('ifge', 156, 2),
    array('ifgt', 157, 2),
    array('ifle', 158, 2),
    array('if_icmpeq', 159, 2),
    array('if_icmpne', 160, 2),
    array('if_icmplt', 161, 2),
    array('if_icmpge', 162, 2),
    array('if_icmpgt', 163, 2),
    array('if_icmple', 164, 2),
    array('if_acmpeq', 165, 2),
    array('if_acmpne', 166, 2),
    array('goto', 167, 2),
    array('jsr', 168, 2),
    array('ret', 169, 1),
    array('tableswitch', 170, -1),
    array('lookupswitch', 171, -1),
    array('ireturn', 172, 0),
    array('lreturn', 173, 0),
    array('freturn', 174, 0),
    array('dreturn', 175, 0),
    array('areturn', 176, 0),
    array('return', 177, 0),
    array('getstatic', 178, 2),
    array('putstatic', 179, 2),
    array('getfield', 180, 2),
    array('putfield', 181, 2),
    array('invokevirtual', 182, 2),
    array('invokespecial', 183, 2),
    array('invokestatic', 184, 2),
    array('invokeinterface', 185, 5),
    array('reserved_invalid', 186, 0),
    array('new', 187, 2),
    array('newarray', 188, 1),
    array('anewarray', 189, 2),
    array('arraylength', 190, 0),
    array('athrow', 191, 0),
    array('checkcast', 192, 2),
    array('instanceof', 193, 2),
    array('monitorenter', 194, 0),
    array('monitorexit', 195, 0),
    array('wide', 196, -1),
    array('multianewarray', 197, 3),
    array('ifnull', 198, 2),
    array('ifnonnull', 199, 2),
    array('goto_w', 200, 4),
    array('jsr_w', 201, 4),
    array('breakpoint', 202, 0),
    array('ldc_quick', 203, 1),
    array('ldc_w_quick', 204, 2),
    array('ldc2_w_quick', 205, 2),
    array('getfield_quick', 206, 2),
    array('putfield_quick', 207, 2),
    array('getfield2_quick', 208, 2),
    array('putfield2_quick', 209, 2),
    array('getstatic_quick', 210, 2),
    array('putstatic_quick', 211, 2),
    array('getstatic2_quick', 212, 2),
    array('putstatic2_quick', 213, 2),
    array('invokevirtual_quick', 214, 2),
    array('invokenonvirtual_quick', 215, 2),
    array('invokesuper_quick', 216, 2),
    array('invokestatic_quick', 217, 2),
    array('invokeinterface_quick', 218, 4),
    array('invokevirtualobject_quick', 219, 2),
    array('invokeignored_quick', 220, 2),
    array('new_quick', 221, 2),
    array('anewarray_quick', 222, 2),
    array('multianewarray_quick', 223, 3),
    array('checkcast_quick', 224, 2),
    array('instanceof_quick', 225, 2),
    array('invokevirtual_quick_w', 226, 2),
    array('getfield_quick_w', 227, 2),
    array('putfield_quick_w', 228, 2),
    array('nonnull_quick', 229, 0),
    array('reserved_invalid', 230, 0),
    array('reserved_invalid', 231, 0),
    array('reserved_invalid', 232, 0),
    array('reserved_invalid', 233, 0),
    array('reserved_invalid', 234, 0),
    array('reserved_invalid', 235, 0),
    array('reserved_invalid', 236, 0),
    array('reserved_invalid', 237, 0),
    array('reserved_invalid', 238, 0),
    array('reserved_invalid', 239, 0),
    array('reserved_invalid', 240, 0),
    array('reserved_invalid', 241, 0),
    array('reserved_invalid', 242, 0),
    array('reserved_invalid', 243, 0),
    array('reserved_invalid', 244, 0),
    array('reserved_invalid', 245, 0),
    array('reserved_invalid', 246, 0),
    array('reserved_invalid', 247, 0),
    array('reserved_invalid', 248, 0),
    array('reserved_invalid', 249, 0),
    array('reserved_invalid', 250, 0),
    array('reserved_invalid', 251, 0),
    array('reserved_invalid', 252, 0),
    array('reserved_invalid', 253, 0),
    array('software', 254, 0),
    array('hardware', 255, 0),
);